nonebot_plugin_tweet/__init__.py
nonebot_plugin_tweet/config.py
nonebot_plugin_tweet/utils.py
nonebot_plugin_tweet-0.3.0.dist-info/licenses/LICENSE
nonebot_plugin_tweet-0.3.0.dist-info/METADATA
nonebot_plugin_tweet-0.3.0.dist-info/WHEEL
nonebot_plugin_tweet-0.3.0.dist-info/entry_points.txt
nonebot_plugin_tweet-0.3.0.dist-info/top_level.txt
nonebot_plugin_tweet-0.3.0.dist-info/RECORD
