Metadata-Version: 2.4
Name: nonebot-plugin-tweet
Version: 0.3.0
Summary: NoneBot2 plugin for forwarding tweets with optional translation support
Author-email: crazt <i@crazt.moe>
Project-URL: Homepage, https://github.com/icrazt/nonebot_tweet
Project-URL: Repository, https://github.com/icrazt/nonebot_tweet
Project-URL: Issues, https://github.com/icrazt/nonebot_tweet/issues
Keywords: bot,qq,nonebot,onebot,twitter
Classifier: Development Status :: 4 - Beta
Classifier: Framework :: AsyncIO
Classifier: Operating System :: OS Independent
Classifier: Programming Language :: Python :: 3
Classifier: Programming Language :: Python :: 3 :: Only
Classifier: Topic :: Communications :: Chat
Classifier: Topic :: Internet :: WWW/HTTP
Requires-Python: <4.0,>=3.9
License-File: LICENSE
Requires-Dist: nonebot2[fastapi]<3.0.0,>=2.4.0
Requires-Dist: nonebot-adapter-onebot<3.0.0,>=2.4.0
Requires-Dist: httpx<1.0.0,>=0.26.0
Requires-Dist: beautifulsoup4<5.0.0,>=4.12.0
Requires-Dist: pydantic<3.0.0,>=2.6.0
Requires-Dist: pydantic-settings<3.0.0,>=2.2.0
Dynamic: license-file
